README.md
pyproject.toml
mcnparse/__init__.py
mcnparse/core.py
mcnparse/cli/__init__.py
mcnparse/cli/__main__.py
mcnparse/cli/core.py
mcnparse/tables/__init__.py
mcnparse/tables/core.py
mcnparse/tallies/__init__.py
mcnparse/tallies/core.py
mcnparse/utils/__init__.py
mcnparse/utils/deserialization.py
mcnparse/utils/functions.py
mcnparse/utils/logs.py
mcnparse/utils/serialization.py
mcnparse/utils/types.py
mcnparse-0.5.1.dist-info/METADATA
mcnparse-0.5.1.dist-info/WHEEL
mcnparse-0.5.1.dist-info/RECORD
