Metadata-Version: 2.3
Name: mcnparse
Version: 0.5.1
Summary: Your package description
Author-email: Your Name <your.email@example.com>
Requires-Python: >=3.11
Requires-Dist: numpy
Requires-Dist: pandas
Requires-Dist: pyarrow
